LICENSE
README.md
setup.py
kofancytool/__init__.py
kofancytool/your_func.py
kofancytool.egg-info/PKG-INFO
kofancytool.egg-info/SOURCES.txt
kofancytool.egg-info/dependency_links.txt
kofancytool.egg-info/top_level.txt